yo_ds/__init__.py
yo_ds/kraken/__init__.py
yo_ds/metrics/__init__.py
yo_ds/metrics/computing.py
yo_ds/metrics/roc_auc.py
yo_ds/tools/__init__.py
yo_ds/tools/_common.py
yo_ds/tools/_maybe.py
yo_ds/tools/misc.py
yo_ds/tools/plots/__init__.py
yo_ds/tools/plots/_common.py
yo_ds/tools/plots/fluent_plot.py
yo_ds/tools/plots/grbar.py
yo_ds/tools/plots/pie.py
yo_ds/tools/plots/roc_auc_plot.py
yo_ds__tests/__init__.py
yo_ds__tests/common.py
yo_ds__tests/test_kraken.py
yo_ds__tests/test_kraken_additional_methods.py
yo_ds__tests/test_metrics.py
yo_ds__tests/test_plots/__init__.py
yo_ds__tests/test_plots/common.py
yo_ds__tests/test_plots/test_fluent_plot.py
yo_ds__tests/test_plots/test_grbar.py
yo_ds__tests/test_plots/test_other_plots.py
yo_ds__tests/test_plots/test_plots_demo.py
yo_ds__tests/test_plots/test_plots_misc.py
yo_ds__tests/test_yo_misc/__init__.py
yo_ds__tests/test_yo_misc/test_yo_misc.py
yo_extensions/__init__.py
yo_extensions/alg/__init__.py
yo_extensions/fluq/__init__.py
yo_extensions/misc/__init__.py
yo_extensions/misc/deprecated.py
yo_extensions/plots/__init__.py
yo_extensions__tests/__init__.py
yo_extensions__tests/test_compatibility.py
yo_ds-1.1.11.dist-info/METADATA
yo_ds-1.1.11.dist-info/WHEEL
yo_ds-1.1.11.dist-info/top_level.txt
yo_ds-1.1.11.dist-info/RECORD
