Metadata-Version: 2.1
Name: yo-ds
Version: 1.1.11
Summary: Personal library with data science tools
Home-page: http://github.com/okulovsky/yo_ds
Author: Yuri Okulovsky
Author-email: yuri.okulovsky@gmail.com
License: MIT
Platform: UNKNOWN
Classifier: Development Status :: 3 - Alpha
Classifier: License :: OSI Approved :: MIT License
Classifier: Programming Language :: Python :: 3.6
Classifier: Topic :: Software Development :: Libraries :: Python Modules
Requires-Dist: pandas
Requires-Dist: matplotlib
Requires-Dist: numpy
Requires-Dist: tqdm
Requires-Dist: seaborn
Requires-Dist: pyaml
Requires-Dist: jsonpickle
Requires-Dist: ipython
Requires-Dist: ipywidgets
Requires-Dist: yo-fluq-ds (==1.1.11)
